{
    "infoSection": {
        "title": "Reach Out To Us",
        "locationLink": "https://www.google.com/maps/place/Alaaeddine+Hospital/@33.45967,35.288912,18.17z/data=!4m6!3m5!1s0x151ef4b10777aea3:0xffd8bd180ec116f3!8m2!3d33.4597435!4d35.2893823!16s%2Fg%2F1tg5fbgq?entry=ttu",
        "infos": [
            {
                "title": "Email",
                "imgSrc": "/email.svg",
                "paragraphs": [
                    {
                        "content": "epms.lb@gmail.com",
                        "paragraphListType": ""
                    },
                    {
                        "content": "Info@epmslb.com",
                        "paragraphListType": ""
                    }
                ]
            },
            {
                "title": "Address",
                "imgSrc": "/location.svg",
                "paragraphs": [
                    {
                        "content": "Alaeddine Bldg, Sarafand, Lebanon",
                        "paragraphListType": ""
                    }
                ]
            },
            {
                "title": "Phone",
                "imgSrc": "/phone.svg",
                "paragraphs": [
                    {
                        "content": "+ 961 3 87 60 98",
                        "paragraphListType": ""
                    },
                    {
                        "content": "+ 961 81 61 71 78",
                        "paragraphListType": ""
                    },
                    {
                        "content": "+ 961 70 28 00 45",
                        "paragraphListType": ""
                    }
                ]
            }
        ]
    },
    "formSection": {
        "title": "Send us a message",
        "paragraphs": [
            {
                "content": "Let us know what you think of our products.",
                "paragraphListType": ""
            },
            {
                "content": "If there is anything we can help you with, we are just a message away.",
                "paragraphListType": ""
            }
        ],
        "submitButtonText": "SUBMIT",
        "submitSuccessMessage": "Email Sent!",
        "submitFailureMessage": "Something went wrong. Please retry after some time.",
        "submitBadFormMessage": "Please follow the form guidelines.",
        "forms": {
            "fname": {
                "label": "First Name",
                "placeholder": "Enter your first name",
                "required": true,
                "formControlProps": {
                    "variant": "filled"
                }
            },
            "lname": {
                "label": "Last Name",
                "placeholder": "Enter your last name",
                "required": true,
                "formControlProps": {
                    "variant": "filled"
                }
            },
            "email": {
                "label": "Email",
                "placeholder": "Enter your email address",
                "regex": "^[a-zA-Z0-9._+-]+@[a-zA-Z0-9.-]+[.][a-zA-Z]{2,}$",
                "required": true,
                "formControlProps": {
                    "variant": "filled"
                }
            },
            "phone": {
                "label": "Phone Number",
                "placeholder": "Enter your phone number",
                "regex": "^(?:03[0-9]{6}|7[01][0-9]{6}|76[0-9]{6}|78[0-9]{6}|79[0-9]{6}|80[0-9]{6}|81[0-9]{6}|0[1-9][0-9]{6})$",
                "formControlProps": {
                    "variant": "filled"
                }
            },
            "msg": {
                "label": "Message",
                "placeholder": "Enter your message",
                "required": true,
                "formControlProps": {
                    "variant": "filled",
                    "multiline": true,
                    "rows": "4"
                }
            }
        }
    }
}